zyxxy/MY_yyyyy_SETTINGS_demo.py
zyxxy/MY_yyyyy_SETTINGS_general.py
zyxxy/MY_yyyyy_SETTINGS_widgets.py
zyxxy/__init__.py
zyxxy/demo_all_yyyyy_shapes.py
zyxxy/demo_yyyyy_shape.py
zyxxy/demo_yyyyy_shape_helper.py
zyxxy/yyyyy_all_EXAMPLES.py
zyxxy/yyyyy_animation.py
zyxxy/yyyyy_bbox.py
zyxxy/yyyyy_canvas.py
zyxxy/yyyyy_clean.py
zyxxy/yyyyy_colors.py
zyxxy/yyyyy_coordinates.py
zyxxy/yyyyy_docs.py
zyxxy/yyyyy_files.py
zyxxy/yyyyy_layers.py
zyxxy/yyyyy_shape_class.py
zyxxy/yyyyy_shape_functions.py
zyxxy/yyyyy_shape_style.py
zyxxy/yyyyy_tests.py
zyxxy/yyyyy_utils.py
zyxxy/yyyyy_widgets.py
zyxxy/yyyyy_word_bubbles.py
zyxxy-0.1.dist-info/METADATA
zyxxy-0.1.dist-info/WHEEL
zyxxy-0.1.dist-info/licenses/LICENSE
zyxxy-0.1.dist-info/RECORD
